deltapy
