Metadata-Version: 1.0
Name: deltapy
Version: 0.0.7
Summary: Data Transformation and Augmentation
Home-page: https://github.com/firmai/deltapy
Author: snowde
Author-email: d.snow@firmai.org
License: MIT
Platform: UNKNOWN
